[{"tag":"h3","refreshOnChange":true,"content":"Search Query Form for Monster Employee Boolean Search","key":"label","input":false,"tableView":false,"label":"Label","type":"label","placeholder":"","prefix":"","customClass":"","suffix":"","multiple":false,"defaultValue":null,"protected":false,"unique":false,"persistent":false,"hidden":false,"clearOnHide":true,"refreshOn":"","redrawOn":"","modalEdit":false,"labelPosition":"top","description":"","errorLabel":"","tooltip":"","hideLabel":false,"tabindex":"","disabled":false,"autofocus":false,"dbIndex":false,"customDefaultValue":"","calculateValue":"","widget":null,"attributes":{},"validateOn":"change","validate":{"required":false,"custom":"","customPrivate":false,"strictDateValidation":false,"multiple":false,"unique":false},"conditional":{"show":null,"when":null,"eq":""},"overlay":{"style":"","left":"","top":"","width":"","height":""},"allowCalculateOverride":false,"encrypted":false,"showCharCount":false,"showWordCount":false,"properties":{},"allowMultipleMasks":false,"attrs":[],"id":"e7hoqyo"},{"tag":"p","refreshOnChange":true,"content":"Enter the query below and ensure the Monster Employee Website is opened","key":"label1","input":false,"placeholder":"","prefix":"","customClass":"","suffix":"","multiple":false,"defaultValue":null,"protected":false,"unique":false,"persistent":false,"hidden":false,"clearOnHide":true,"refreshOn":"","redrawOn":"","tableView":false,"modalEdit":false,"label":"Label","labelPosition":"top","description":"","errorLabel":"","tooltip":"","hideLabel":false,"tabindex":"","disabled":false,"autofocus":false,"dbIndex":false,"customDefaultValue":"","calculateValue":"","widget":null,"attributes":{},"validateOn":"change","validate":{"required":false,"custom":"","customPrivate":false,"strictDateValidation":false,"multiple":false,"unique":false},"conditional":{"show":null,"when":null,"eq":""},"overlay":{"style":"","left":"","top":"","width":"","height":""},"allowCalculateOverride":false,"encrypted":false,"showCharCount":false,"showWordCount":false,"properties":{},"allowMultipleMasks":false,"type":"label","attrs":[],"id":"ex0dkjm"},{"label":"Search Field:","labelPosition":"top","placeholder":"","description":"Perform search using Boolean Operations (AND, OR, NOT)","widget":{"type":"input"},"hidden":false,"hideLabel":false,"showWordCount":false,"showCharCount":false,"disabled":false,"tableView":true,"validateOn":"change","validate":{"required":true,"pattern":"","customMessage":"","minLength":"","maxLength":"","minWords":"","maxWords":"","custom":"","customPrivate":false,"strictDateValidation":false,"multiple":false,"unique":false},"errorLabel":"","key":"skillset","conditional":{"show":null,"when":null,"eq":""},"type":"textarea","rows":1,"wysiwyg":false,"input":true,"prefix":"","customClass":"","suffix":"","multiple":false,"protected":false,"unique":false,"persistent":true,"clearOnHide":true,"refreshOn":"","redrawOn":"","modalEdit":false,"tooltip":"","tabindex":"","autofocus":false,"dbIndex":false,"customDefaultValue":"","calculateValue":"","attributes":{},"overlay":{"style":"","left":"","top":"","width":"","height":""},"allowCalculateOverride":false,"encrypted":false,"properties":{},"allowMultipleMasks":false,"mask":false,"inputType":"text","inputFormat":"html","inputMask":"","editor":"","id":"ekoddn","defaultValue":""},{"label":"Minimum Year","labelPosition":"top","placeholder":"eg. 1","description":"","prefix":"","suffix":"","widget":{"type":"input"},"inputMask":"","hidden":false,"hideLabel":false,"showWordCount":false,"showCharCount":false,"disabled":false,"tableView":true,"validateOn":"change","validate":{"required":true,"pattern":"","customMessage":"","minLength":"","maxLength":"","custom":"","customPrivate":false,"strictDateValidation":false,"multiple":false,"unique":false},"errorLabel":"","key":"minyear","conditional":{"show":null,"when":null,"eq":""},"type":"textfield","input":true,"customClass":"","multiple":false,"protected":false,"unique":false,"persistent":true,"clearOnHide":true,"refreshOn":"","redrawOn":"","modalEdit":false,"tooltip":"","tabindex":"","autofocus":false,"dbIndex":false,"customDefaultValue":"","calculateValue":"","attributes":{},"overlay":{"style":"","left":"","top":"","width":"","height":""},"allowCalculateOverride":false,"encrypted":false,"properties":{},"allowMultipleMasks":false,"mask":false,"inputType":"text","inputFormat":"plain","id":"em634qt","defaultValue":""},{"label":"Maximum Year","labelPosition":"top","placeholder":"eg. 3","description":"","prefix":"","suffix":"","widget":{"type":"input"},"inputMask":"","hidden":false,"hideLabel":false,"showWordCount":false,"showCharCount":false,"disabled":false,"tableView":true,"validateOn":"change","validate":{"required":false,"pattern":"","customMessage":"","minLength":"","maxLength":"","custom":"","customPrivate":false,"strictDateValidation":false,"multiple":false,"unique":false},"errorLabel":"","key":"maxyear","conditional":{"show":null,"when":null,"eq":""},"type":"textfield","input":true,"customClass":"","multiple":false,"protected":false,"unique":false,"persistent":true,"clearOnHide":true,"refreshOn":"","redrawOn":"","modalEdit":false,"tooltip":"","tabindex":"","autofocus":false,"dbIndex":false,"customDefaultValue":"","calculateValue":"","attributes":{},"overlay":{"style":"","left":"","top":"","width":"","height":""},"allowCalculateOverride":false,"encrypted":false,"properties":{},"allowMultipleMasks":false,"mask":false,"inputType":"text","inputFormat":"plain","id":"eu73cfo","defaultValue":""},{"label":"Country","labelPosition":"top","widget":"choicesjs","placeholder":"Select a country","description":"","hidden":false,"hideLabel":false,"disabled":false,"tableView":true,"data":{"resource":"","json":"","url":"","values":[{"value":"Singapore","label":"Singapore"},{"label":"Malaysia","value":"Malaysia"}],"custom":""},"valueProperty":"","template":"<span>{{ item.label }}</span>","readOnlyValue":false,"validateOn":"change","validate":{"required":true,"customMessage":"","custom":"","customPrivate":false,"strictDateValidation":false,"multiple":false,"unique":false},"errorLabel":"","key":"country","conditional":{"show":null,"when":null,"eq":""},"logic":[],"type":"select","indexeddb":{"filter":{}},"selectFields":"","searchField":"","minSearch":0,"filter":"","limit":100,"refreshOn":"","input":true,"prefix":"","customClass":"","suffix":"","multiple":false,"protected":false,"unique":false,"persistent":true,"clearOnHide":true,"redrawOn":"","modalEdit":false,"tooltip":"","tabindex":"","autofocus":false,"dbIndex":false,"customDefaultValue":"","calculateValue":"","attributes":{},"overlay":{"style":"","left":"","top":"","width":"","height":""},"allowCalculateOverride":false,"encrypted":false,"showCharCount":false,"showWordCount":false,"properties":{},"allowMultipleMasks":false,"clearOnRefresh":false,"dataSrc":"values","lazyLoad":true,"searchEnabled":true,"authenticate":false,"searchThreshold":0.3,"fuseOptions":{"include":"score","threshold":0.3},"customOptions":{},"id":"e9yf1xj","defaultValue":""},{"label":"Nationality","labelPosition":"top","widget":"choicesjs","placeholder":"Select a nationality","description":"","hidden":false,"hideLabel":false,"disabled":false,"tableView":true,"data":{"resource":"","json":"","url":"","values":[{"value":"afghan","label":"Afghan"},{"label":"Albanian","value":"albanian"},{"label":"Algerian","value":"algerian"},{"label":"American Samoa","value":"american samoa"},{"label":"Andorra","value":"andorra"},{"label":"Angola","value":"angola"},{"label":"Anguilla","value":"anguilla"},{"label":"Antarctica","value":"antarctica"},{"label":"Antigua and Barbuda","value":"antigua And Barbuda"},{"label":"Argentina","value":"argentina"},{"label":"Armenia","value":"armenia"},{"label":"Aruba","value":"aruba"},{"label":"Australian","value":"australian"},{"label":"Austria","value":"austria"},{"label":"Azerbaijan","value":"azerbaijan"},{"label":"Bahamas","value":"bahamas"},{"label":"Bahraini","value":"bahraini"},{"label":"Bangladeshi","value":"bangladeshi"},{"label":"Barbados","value":"barbados"},{"label":"Belarus","value":"belarus"},{"label":"Belgium","value":"belgium"},{"label":"Belize","value":"belize"},{"label":"Benin","value":"benin"},{"label":"Bermuda","value":"bermuda"},{"label":"Bhutan","value":"bhutan"},{"label":"Bolivia","value":"bolivia"},{"label":"Bosnia and Herzegovina","value":"bosnia and herzegovina"},{"label":"Botswana","value":"botswana"},{"label":"Bouvet Island","value":"bouvet Island"},{"label":"Brazil","value":"brazil"},{"label":"British Indian Ocean Territory","value":"british Indian Ocean Territory"},{"label":"Brunei Darussalam","value":"brunei darussalam"},{"label":"Bulgaria","value":"bulgaria"},{"label":"Burkina Faso","value":"burkina Faso"},{"label":"Burundi","value":"burundi"},{"label":"Cambodia","value":"cambodia"},{"label":"Cameroon","value":"cameroon"},{"label":"Canadian","value":"canadian"},{"label":"Cape Verde","value":"cape Verde"},{"label":"Cayman Islands","value":"cayman Islands"},{"label":"Central African Republic","value":"central African Republic"},{"label":"Chad","value":"chad"},{"label":"Chile","value":"chile"},{"label":"Chinese","value":"chinese"},{"label":"Christmas Island","value":"christmas Island"},{"label":"Cocos (Keeling) Islands","value":"cocos"},{"label":"Colombia","value":"colombia"},{"label":"Comoros","value":"comoros"},{"label":"Congo","value":"congo"},{"label":"Congo, the Democratic Republic","value":"congo, the democratic Republic"},{"label":"Cook Islands","value":"cook Islands"},{"label":"Costa Rica","value":"costa Rica"},{"label":"Cote D'Ivoire","value":"cote D'Ivoire"},{"label":"Croatia","value":"croatia"},{"label":"Cuba","value":"cuba"},{"label":"Cyprus","value":"cyprus"},{"label":"Czech Republic","value":"czech Republic"},{"label":"Denmark","value":"denmark"},{"label":"Djibouti","value":"djibouti"},{"label":"Dominica","value":"dominica"},{"label":"Dominican Rebublic","value":"dominicanRebublic"},{"label":"Ecuador","value":"ecuador"},{"label":"Egyptian","value":"egyptian"},{"label":"El Salvador","value":"el Salvador"},{"label":"Emirati/UAE","value":"emirati/Uae"},{"label":"Equatorial Guinea","value":"equatorial Guinea"},{"label":"Eritrea","value":"eritrea"},{"label":"Estonia","value":"estonia"},{"label":"Ethiopia","value":"ethiopia"},{"label":"Falkland Islands (Malvinas)","value":"falkland Islands"},{"label":"Faroe Islands","value":"faroe Islands"},{"label":"Fiji","value":"fiji"},{"label":"Finland","value":"finland"},{"label":"French","value":"french"},{"label":"French Guiana","value":"french Guiana"},{"label":"French Polynesia","value":"french Polynesia"},{"label":"French Southern Territories","value":"french Southern Territories"},{"label":"Gabon","value":"gabon"},{"label":"Gambia","value":"gambia"},{"label":"Georgia","value":"georgia"},{"label":"German","value":"german"},{"label":"Ghana","value":"ghana"},{"label":"Gibraltar","value":"gibraltar"},{"label":"Greece","value":"greece"},{"label":"Greenland","value":"greenland"},{"label":"Grenada","value":"grenada"},{"label":"Guadeloupe","value":"guadeloupe"},{"label":"Guam","value":"guam"},{"label":"Guatemala","value":"guatemala"},{"label":"Guinea","value":"guinea"},{"label":"Guinea-Bissau","value":"guinea-Bissau"},{"label":"Guyana","value":"guyana"},{"label":"Haiti","value":"haiti"},{"label":"Heard Island and Mcdonald Island","value":"heard Island And Mcdonald Island"},{"label":"Holy See (Vatican City State)","value":"holy See"},{"label":"Honduras","value":"honduras"},{"label":"Hong Kong","value":"hongKong"},{"label":"Hungary","value":"hungary"},{"label":"Iceland","value":"iceland"},{"label":"Indian","value":"indian"},{"label":"Indonesian","value":"indonesian"},{"label":"Iranian","value":"iranian"},{"label":"Iraqi","value":"iraqi"},{"label":"Ireland","value":"ireland"},{"label":"Israel","value":"israel"},{"label":"Italian","value":"italian"},{"label":"Jamaica","value":"jamaica"},{"label":"Japan","value":"japan"},{"label":"Jordanian","value":"jordanian"},{"label":"Kazakhstan","value":"kazakhstan"},{"label":"Kenyan","value":"kenyan"},{"label":"Kiribati","value":"kiribati"},{"label":"Korea, Democratic People's Republic","value":"korea, Democratic People "},{"label":"Korea , Republic of","value":"korea, Republic Of"},{"label":"Kuwaiti","value":"kuwaiti"},{"label":"Kyrgyzstan","value":"kyrgyzstan"},{"label":"Lao","value":"lao"},{"label":"Latvia","value":"latvia"},{"label":"Lebanese","value":"lebanese"},{"label":"Lesotho","value":"lesotho"},{"label":"Liberia","value":"liberia"},{"label":"Libyan Arab Jamahiriya","value":"libyan Arab Jamahiriya"},{"label":"Liechtenstein","value":"liechtenstein"},{"label":"Lithuania","value":"lithuania"},{"label":"Luxembourg","value":"luxembourg"},{"label":"Macao","value":"macao"},{"label":"Macedonia","value":"macedonia"},{"label":"Madagascar","value":"madagascar"},{"label":"Malawi","value":"malawi"},{"label":"Malaysian","value":"malaysian"},{"label":"Maldives","value":"maldives"},{"label":"Mali","value":"mali"},{"label":"Malta","value":"malta"},{"label":"Marshall Islands","value":"marshallIslands"},{"label":"Martinique","value":"martinique"},{"label":"Mauritania","value":"mauritania"},{"label":"Mauritius","value":"mauritius"},{"label":"Mayotte","value":"mayotte"},{"label":"Mexico","value":"mexico"},{"label":"Micronesia","value":"micronesia"},{"label":"Moldova","value":"moldova"},{"label":"Monaco","value":"monaco"},{"label":"Mongolia","value":"mongolia"},{"label":"Montserrat","value":"montserrat"},{"label":"Moroccan","value":"moroccan"},{"label":"Mozambique","value":"mozambique"},{"label":"Myanmar","value":"myanmar"},{"label":"Namibia","value":"namibia"},{"label":"Nauru","value":"nauru"},{"label":"Nepalese","value":"nepalese"},{"label":"Netherlands","value":"netherlands"},{"label":"Netherlands Antilles","value":"netherlands Antilles"},{"label":"New Caledonia","value":"new Caledonia"},{"label":"New Zealand","value":"newZealand"},{"label":"Nicaragua","value":"nicaragua"},{"label":"Niger","value":"niger"},{"label":"Nigerian","value":"nigerian"},{"label":"Niue","value":"niue"},{"label":"Norfolk Island","value":"norfolk Island"},{"label":"Northern Mariana Islands","value":"northern Mariana Islands"},{"label":"Norway","value":"norway"},{"label":"Omani","value":"omani"},{"label":"Pakistani","value":"pakistani"},{"label":"Palau","value":"palau"},{"label":"Palestinian Territory","value":"palestinian Territory"},{"label":"Panama","value":"panama"},{"label":"Papua New Guinea","value":"papua New Guinea"},{"label":"Paraguay","value":"paraguay"},{"label":"Peru","value":"peru"},{"label":"Philippines/Filipino","value":"philippines/Filipino"},{"label":"Pitcairn","value":"pitcairn"},{"label":"Poland","value":"poland"},{"label":"Portugal","value":"portugal"},{"label":"Puerto Rico","value":"puerto Rico"},{"label":"Qatari","value":"qatari"},{"label":"Reunion","value":"reunion"},{"label":"Romania","value":"romania"},{"label":"Russian","value":"russian"},{"label":"Rwanda","value":"rwanda"},{"label":"Saint Helena","value":"saint Helena"},{"label":"Saint Kitts and Nevis","value":"saint Kitts And Nevis"},{"label":"Saint Lucia","value":"saint Lucia"},{"label":"Saint Pierre and Miquelon","value":"saint Pierre"},{"label":"Saint Vincent and the Grenadines","value":"saint Vincent And The Grenadines "},{"label":"Samoa","value":"samoa"},{"label":"San Marino","value":"san Marino"},{"label":"Sao Tome and Principe","value":"sao Tome And Principe"},{"label":"Saudi Arabian","value":"saudi Arabian"},{"label":"Senegal","value":"senegal"},{"label":"Serbia and Montenegro","value":"serbia And Montenegro"},{"label":"Seychelles","value":"seychelles"},{"label":"Sierra Leone","value":"sierra Leone"},{"label":"Singaporean","value":"singaporean"},{"label":"Slovakia","value":"slovakia"},{"label":"Slovenia","value":"slovenia"},{"label":"Soloman Islands","value":"soloman Islands"},{"label":"Somalia","value":"somalia"},{"label":"South African","value":"south African"},{"label":"South Georgia and the South Sandwich Islands","value":"south Georgia"},{"label":"Spanish","value":"spanish"},{"label":"Sri Lankan","value":"sri Lankan"},{"label":"Sudanese","value":"sudanese"},{"label":"Suriname","value":"suriname"},{"label":"Svalbard and Jan Mayen","value":"svalbard And Jan Mayen"},{"label":"Swaziland","value":"swaziland"},{"label":"Swedan","value":"swedan"},{"label":"Switzerland","value":"switzerland"},{"label":"Syrian","value":"syrian"},{"label":"Taiwanese","value":"taiwanese"},{"label":"Tajikistan","value":"tajikistan"},{"label":"Tanzania, United Republic of","value":"tanzania United Republic Of"},{"label":"Thai","value":"thai"},{"label":"Timor-Leste","value":"timor-Leste"},{"label":"Tongo","value":"tongo"},{"label":"Tokelau","value":"tokelau"},{"label":"Tonga","value":"tonga"},{"label":"Trinidad and Tobago","value":"trinidad And Tobago"},{"label":"Tunisia","value":"tunisia"},{"label":"Turkey","value":"turkey"},{"label":"Turkmenistan","value":"turkmenistan"},{"label":"Turks and Caicos Islands","value":"turks And Caicos Islands"},{"label":"Tuvalu","value":"tuvalu"},{"label":"Uganda","value":"uganda"},{"label":"Ukraine","value":"ukraine"},{"label":"United Kingdom","value":"united Kingdom"},{"label":"United States","value":"united States"},{"label":"United States Minor Outlying Islands","value":"united States MinorOutlying Islands"},{"label":"Uruguay","value":"uruguay"},{"label":"Uzbekistan","value":"uzbekistan"},{"label":"Vanuatu","value":"vanuatu"},{"label":"Venezuela","value":"venezuela"},{"label":"Vietnamese","value":"vietnamese"},{"label":"Virgin Islands, British","value":"virgin Islands, British"},{"label":"Virgin Islands, U.s.","value":"virgin Islands, U.S"},{"label":"Wallis and Futuna","value":"wallis And Futuna"},{"label":"Western Sahara","value":"western Sahara"},{"label":"Yemeni","value":"yemeni"},{"label":"Zambia","value":"zambia"},{"label":"Zimbabwe","value":"zimbabwe"}],"custom":""},"valueProperty":"","template":"<span>{{ item.label }}</span>","readOnlyValue":false,"validateOn":"change","validate":{"required":true,"customMessage":"","custom":"","customPrivate":false,"strictDateValidation":false,"multiple":false,"unique":false},"errorLabel":"","key":"nationality","conditional":{"show":null,"when":null,"eq":""},"logic":[],"type":"select","indexeddb":{"filter":{}},"selectFields":"","searchField":"","minSearch":0,"filter":"","limit":100,"refreshOn":"","input":true,"prefix":"","customClass":"","suffix":"","multiple":false,"protected":false,"unique":false,"persistent":true,"clearOnHide":true,"redrawOn":"","modalEdit":false,"tooltip":"","tabindex":"","autofocus":false,"dbIndex":false,"customDefaultValue":"","calculateValue":"","attributes":{},"overlay":{"style":"","left":"","top":"","width":"","height":""},"allowCalculateOverride":false,"encrypted":false,"showCharCount":false,"showWordCount":false,"properties":{},"allowMultipleMasks":false,"clearOnRefresh":false,"dataSrc":"values","lazyLoad":true,"searchEnabled":true,"authenticate":false,"searchThreshold":0.3,"fuseOptions":{"include":"score","threshold":0.3},"customOptions":{},"id":"en61ux7","defaultValue":""},{"label":"Include PR","description":"","hidden":false,"hideLabel":false,"disabled":false,"tableView":false,"validate":{"required":false,"customMessage":"","custom":"","customPrivate":false,"strictDateValidation":false,"multiple":false,"unique":false},"errorLabel":"","key":"includePr","conditional":{"show":null,"when":null,"eq":""},"type":"checkbox","input":true,"placeholder":"","prefix":"","customClass":"","suffix":"","multiple":false,"protected":false,"unique":false,"persistent":true,"clearOnHide":true,"refreshOn":"","redrawOn":"","modalEdit":false,"labelPosition":"right","tooltip":"","tabindex":"","autofocus":false,"dbIndex":false,"customDefaultValue":"","calculateValue":"","widget":null,"attributes":{},"validateOn":"change","overlay":{"style":"","left":"","top":"","width":"","height":""},"allowCalculateOverride":false,"encrypted":false,"showCharCount":false,"showWordCount":false,"properties":{},"allowMultipleMasks":false,"inputType":"checkbox","dataGridLabel":true,"value":"","name":"","id":"evr4rmr","defaultValue":false,"labelWidth":50,"labelMargin":3},{"label":"Search by Month","labelPosition":"top","widget":"choicesjs","placeholder":"Choose an option","description":"","hidden":false,"hideLabel":false,"disabled":false,"tableView":true,"data":{"resource":"","json":"","url":"","values":[{"label":"Last 3 Months","value":"Last 3 Months"},{"value":"Last 6 Months","label":"Last 6 Months"},{"label":"Last 12 Months","value":"Last 12 Months"}],"custom":""},"valueProperty":"","template":"<span>{{ item.label }}</span>","readOnlyValue":false,"validateOn":"change","validate":{"required":true,"customMessage":"","custom":"","customPrivate":false,"strictDateValidation":false,"multiple":false,"unique":false},"errorLabel":"","key":"search","conditional":{"show":null,"when":null,"eq":""},"logic":[],"type":"select","indexeddb":{"filter":{}},"selectFields":"","searchField":"","minSearch":0,"filter":"","limit":100,"refreshOn":"","input":true,"prefix":"","customClass":"","suffix":"","multiple":false,"protected":false,"unique":false,"persistent":true,"clearOnHide":true,"redrawOn":"","modalEdit":false,"tooltip":"","tabindex":"","autofocus":false,"dbIndex":false,"customDefaultValue":"","calculateValue":"","attributes":{},"overlay":{"style":"","left":"","top":"","width":"","height":""},"allowCalculateOverride":false,"encrypted":false,"showCharCount":false,"showWordCount":false,"properties":{},"allowMultipleMasks":false,"clearOnRefresh":false,"dataSrc":"values","lazyLoad":true,"searchEnabled":true,"authenticate":false,"searchThreshold":0.3,"fuseOptions":{"include":"score","threshold":0.3},"customOptions":{},"id":"eupz68","defaultValue":""},{"type":"button","label":"Submit","key":"submit","size":"md","block":false,"action":"submit","disableOnInvalid":true,"theme":"primary","input":true,"placeholder":"","prefix":"","customClass":"","suffix":"","multiple":false,"defaultValue":null,"protected":false,"unique":false,"persistent":false,"hidden":false,"clearOnHide":true,"refreshOn":"","redrawOn":"","tableView":false,"modalEdit":false,"labelPosition":"top","description":"","errorLabel":"","tooltip":"","hideLabel":false,"tabindex":"","disabled":false,"autofocus":false,"dbIndex":false,"customDefaultValue":"","calculateValue":"","widget":{"type":"input"},"attributes":{},"validateOn":"change","validate":{"required":false,"custom":"","customPrivate":false,"strictDateValidation":false,"multiple":false,"unique":false},"conditional":{"show":null,"when":null,"eq":""},"overlay":{"style":"","left":"","top":"","width":"","height":""},"allowCalculateOverride":false,"encrypted":false,"showCharCount":false,"showWordCount":false,"properties":{},"allowMultipleMasks":false,"leftIcon":"","rightIcon":"","dataGridLabel":true,"id":"ejvksa"}]